cloudshell/__init__.py
cloudshell/snmp/__init__.py
cloudshell/snmp/cloudshell_snmp.py
cloudshell/snmp/snmp_configurator.py
cloudshell/snmp/snmp_parameters.py
cloudshell/snmp/types.py
cloudshell/snmp/core/__init__.py
cloudshell/snmp/core/snmp_context_manager.py
cloudshell/snmp/core/snmp_engine.py
cloudshell/snmp/core/snmp_errors.py
cloudshell/snmp/core/snmp_mib_builder.py
cloudshell/snmp/core/snmp_msg_pdu_dsp.py
cloudshell/snmp/core/snmp_response_reader.py
cloudshell/snmp/core/snmp_service.py
cloudshell/snmp/core/snmp_view_controller.py
cloudshell/snmp/core/domain/__init__.py
cloudshell/snmp/core/domain/quali_mib_table.py
cloudshell/snmp/core/domain/snmp_json_record.py
cloudshell/snmp/core/domain/snmp_oid.py
cloudshell/snmp/core/domain/snmp_response.py
cloudshell/snmp/core/tools/__init__.py
cloudshell/snmp/core/tools/mib_builder_helper.py
cloudshell/snmp/core/tools/snmp_constants.py
cloudshell/snmp/core/tools/snmp_context.py
cloudshell/snmp/core/tools/snmp_json_mib.py
cloudshell/snmp/core/tools/snmp_json_mib_parser.py
cloudshell/snmp/core/tools/snmp_parameters_helper.py
cloudshell/snmp/core/tools/snmp_security.py
cloudshell/snmp/core/tools/snmp_trasnport.py
cloudshell/snmp/mibs/ASN1-ENUMERATION.py
cloudshell/snmp/mibs/ASN1-REFINEMENT.py
cloudshell/snmp/mibs/ASN1.py
cloudshell/snmp/mibs/BRIDGE-MIB.json
cloudshell/snmp/mibs/ENTITY-MIB.json
cloudshell/snmp/mibs/EtherLike-MIB.json
cloudshell/snmp/mibs/IANA-ADDRESS-FAMILY-NUMBERS-MIB.json
cloudshell/snmp/mibs/IANA-MAU-MIB.json
cloudshell/snmp/mibs/IANAifType-MIB.json
cloudshell/snmp/mibs/IEEE8023-LAG-MIB.json
cloudshell/snmp/mibs/IF-MIB.json
cloudshell/snmp/mibs/INET-ADDRESS-MIB.json
cloudshell/snmp/mibs/IP-MIB.json
cloudshell/snmp/mibs/IPV6-MIB.json
cloudshell/snmp/mibs/IPV6-TC.json
cloudshell/snmp/mibs/LLDP-MIB.json
cloudshell/snmp/mibs/MAU-MIB.json
cloudshell/snmp/mibs/P-BRIDGE-MIB.json
cloudshell/snmp/mibs/PYSNMP-MIB.py
cloudshell/snmp/mibs/PYSNMP-SOURCE-MIB.py
cloudshell/snmp/mibs/PYSNMP-USM-MIB.py
cloudshell_snmp-5.0.3.dist-info/LICENSE
cloudshell_snmp-5.0.3.dist-info/METADATA
cloudshell_snmp-5.0.3.dist-info/WHEEL
cloudshell_snmp-5.0.3.dist-info/top_level.txt
cloudshell_snmp-5.0.3.dist-info/RECORD
